{
    "source": "https:\/\/www.run2pix.com\/report\/report_w.php?EventCode=20251221&Race=HM&sn=359&pagenum=7",
    "total_records": 500,
    "results": [
        {
            "Bibnr": "34589",
            "Name": "李佳叡",
            "OfficialTime": "01:52:29",
            "RankAll": "3001",
            "NetTime": "01:48:30"
        },
        {
            "Bibnr": "31632",
            "Name": "劉琦允",
            "OfficialTime": "01:52:30",
            "RankAll": "3002",
            "NetTime": "01:46:40"
        },
        {
            "Bibnr": "15157",
            "Name": "張艾鈴",
            "OfficialTime": "01:52:30",
            "RankAll": "3003",
            "NetTime": "01:50:56"
        },
        {
            "Bibnr": "37109",
            "Name": "黃仲宏",
            "OfficialTime": "01:52:30",
            "RankAll": "3004",
            "NetTime": "01:51:41"
        },
        {
            "Bibnr": "31356",
            "Name": "彭士倫",
            "OfficialTime": "01:52:30",
            "RankAll": "3005",
            "NetTime": "01:48:31"
        },
        {
            "Bibnr": "20098",
            "Name": "陳麗娟",
            "OfficialTime": "01:52:30",
            "RankAll": "3006",
            "NetTime": "01:50:12"
        },
        {
            "Bibnr": "14694",
            "Name": "郭宥婕",
            "OfficialTime": "01:52:30",
            "RankAll": "3007",
            "NetTime": "01:50:48"
        },
        {
            "Bibnr": "23276",
            "Name": "劉立智",
            "OfficialTime": "01:52:31",
            "RankAll": "3008",
            "NetTime": "01:49:07"
        },
        {
            "Bibnr": "28515",
            "Name": "許懷瀛",
            "OfficialTime": "01:52:31",
            "RankAll": "3009",
            "NetTime": "01:44:52"
        },
        {
            "Bibnr": "34324",
            "Name": "翁才晉",
            "OfficialTime": "01:52:31",
            "RankAll": "3010",
            "NetTime": "01:49:17"
        },
        {
            "Bibnr": "36460",
            "Name": "洪嘉偉",
            "OfficialTime": "01:52:31",
            "RankAll": "3011",
            "NetTime": "01:50:59"
        },
        {
            "Bibnr": "28148",
            "Name": "章智瑋",
            "OfficialTime": "01:52:32",
            "RankAll": "3012",
            "NetTime": "01:52:16"
        },
        {
            "Bibnr": "26731",
            "Name": "黃玠元",
            "OfficialTime": "01:52:32",
            "RankAll": "3013",
            "NetTime": "01:46:46"
        },
        {
            "Bibnr": "30789",
            "Name": "Tsoi Weng Kuan",
            "OfficialTime": "01:52:32",
            "RankAll": "3014",
            "NetTime": "01:39:46"
        },
        {
            "Bibnr": "27388",
            "Name": "陳陽湶",
            "OfficialTime": "01:52:32",
            "RankAll": "3015",
            "NetTime": "01:52:22"
        },
        {
            "Bibnr": "15038",
            "Name": "黃亞夏",
            "OfficialTime": "01:52:33",
            "RankAll": "3016",
            "NetTime": "01:50:07"
        },
        {
            "Bibnr": "35507",
            "Name": "Lau Hok Yee",
            "OfficialTime": "01:52:33",
            "RankAll": "3017",
            "NetTime": "01:50:09"
        },
        {
            "Bibnr": "31768",
            "Name": "Lau Wai Kwong Johnny",
            "OfficialTime": "01:52:33",
            "RankAll": "3018",
            "NetTime": "01:50:19"
        },
        {
            "Bibnr": "29307",
            "Name": "陳遠仁",
            "OfficialTime": "01:52:34",
            "RankAll": "3019",
            "NetTime": "01:49:21"
        },
        {
            "Bibnr": "22504",
            "Name": "廖奕翔",
            "OfficialTime": "01:52:34",
            "RankAll": "3020",
            "NetTime": "01:49:49"
        },
        {
            "Bibnr": "37381",
            "Name": "鄧森文",
            "OfficialTime": "01:52:34",
            "RankAll": "3021",
            "NetTime": "01:50:19"
        },
        {
            "Bibnr": "25009",
            "Name": "陳泳吉",
            "OfficialTime": "01:52:34",
            "RankAll": "3022",
            "NetTime": "01:50:14"
        },
        {
            "Bibnr": "34020",
            "Name": "黃增長",
            "OfficialTime": "01:52:34",
            "RankAll": "3023",
            "NetTime": "01:49:04"
        },
        {
            "Bibnr": "29302",
            "Name": "俞元凱",
            "OfficialTime": "01:52:34",
            "RankAll": "3024",
            "NetTime": "01:48:56"
        },
        {
            "Bibnr": "30004",
            "Name": "Jimmy Wong",
            "OfficialTime": "01:52:34",
            "RankAll": "3025",
            "NetTime": "01:50:02"
        },
        {
            "Bibnr": "14131",
            "Name": "王禹喬",
            "OfficialTime": "01:52:35",
            "RankAll": "3026",
            "NetTime": "01:51:59"
        },
        {
            "Bibnr": "22193",
            "Name": "翁仁祥",
            "OfficialTime": "01:52:35",
            "RankAll": "3027",
            "NetTime": "01:48:24"
        },
        {
            "Bibnr": "27072",
            "Name": "黃志威",
            "OfficialTime": "01:52:36",
            "RankAll": "3028",
            "NetTime": "01:49:47"
        },
        {
            "Bibnr": "20175",
            "Name": "劉美芳",
            "OfficialTime": "01:52:37",
            "RankAll": "3029",
            "NetTime": "01:51:56"
        },
        {
            "Bibnr": "25447",
            "Name": "蕭旭禾",
            "OfficialTime": "01:52:37",
            "RankAll": "3030",
            "NetTime": "01:50:31"
        },
        {
            "Bibnr": "36627",
            "Name": "麥耕碩",
            "OfficialTime": "01:52:37",
            "RankAll": "3031",
            "NetTime": "01:40:23"
        },
        {
            "Bibnr": "23776",
            "Name": "林士豪",
            "OfficialTime": "01:52:37",
            "RankAll": "3032",
            "NetTime": "01:50:39"
        },
        {
            "Bibnr": "30406",
            "Name": "連偉智",
            "OfficialTime": "01:52:38",
            "RankAll": "3033",
            "NetTime": "01:50:44"
        },
        {
            "Bibnr": "20454",
            "Name": "陳嘉燕",
            "OfficialTime": "01:52:38",
            "RankAll": "3034",
            "NetTime": "01:45:05"
        },
        {
            "Bibnr": "30302",
            "Name": "國又新",
            "OfficialTime": "01:52:38",
            "RankAll": "3035",
            "NetTime": "01:51:16"
        },
        {
            "Bibnr": "20130",
            "Name": "陳昭芬",
            "OfficialTime": "01:52:38",
            "RankAll": "3036",
            "NetTime": "01:51:49"
        },
        {
            "Bibnr": "20267",
            "Name": "Tsui Sin Hang",
            "OfficialTime": "01:52:38",
            "RankAll": "3037",
            "NetTime": "01:50:10"
        },
        {
            "Bibnr": "26405",
            "Name": "LI ZHENG HONG",
            "OfficialTime": "01:52:40",
            "RankAll": "3038",
            "NetTime": "01:44:43"
        },
        {
            "Bibnr": "20404",
            "Name": "黃星婷",
            "OfficialTime": "01:52:40",
            "RankAll": "3039",
            "NetTime": "01:51:47"
        },
        {
            "Bibnr": "20179",
            "Name": "黃琬婷",
            "OfficialTime": "01:52:40",
            "RankAll": "3040",
            "NetTime": "01:48:40"
        },
        {
            "Bibnr": "19506",
            "Name": "邱佳燕",
            "OfficialTime": "01:52:40",
            "RankAll": "3041",
            "NetTime": "01:50:58"
        },
        {
            "Bibnr": "37487",
            "Name": "林弘浦",
            "OfficialTime": "01:52:40",
            "RankAll": "3042",
            "NetTime": "01:48:52"
        },
        {
            "Bibnr": "30280",
            "Name": "賴加和",
            "OfficialTime": "01:52:41",
            "RankAll": "3043",
            "NetTime": "01:46:58"
        },
        {
            "Bibnr": "14533",
            "Name": "梁惠美",
            "OfficialTime": "01:52:41",
            "RankAll": "3044",
            "NetTime": "01:51:40"
        },
        {
            "Bibnr": "23746",
            "Name": "于凡",
            "OfficialTime": "01:52:42",
            "RankAll": "3045",
            "NetTime": "01:49:54"
        },
        {
            "Bibnr": "25779",
            "Name": "楊閔富",
            "OfficialTime": "01:52:42",
            "RankAll": "3046",
            "NetTime": "01:43:18"
        },
        {
            "Bibnr": "19158",
            "Name": "Kwong Tsz Kwan",
            "OfficialTime": "01:52:43",
            "RankAll": "3047",
            "NetTime": "01:52:20"
        },
        {
            "Bibnr": "37150",
            "Name": "黃育仁",
            "OfficialTime": "01:52:43",
            "RankAll": "3048",
            "NetTime": "01:47:24"
        },
        {
            "Bibnr": "32714",
            "Name": "黃堃育",
            "OfficialTime": "01:52:43",
            "RankAll": "3049",
            "NetTime": "01:48:55"
        },
        {
            "Bibnr": "33366",
            "Name": "陳豪男",
            "OfficialTime": "01:52:43",
            "RankAll": "3050",
            "NetTime": "01:51:19"
        },
        {
            "Bibnr": "20147",
            "Name": "邱凰資",
            "OfficialTime": "01:52:43",
            "RankAll": "3051",
            "NetTime": "01:52:01"
        },
        {
            "Bibnr": "28188",
            "Name": "CHOW CHUN KIT",
            "OfficialTime": "01:52:44",
            "RankAll": "3052",
            "NetTime": "01:50:23"
        },
        {
            "Bibnr": "21644",
            "Name": "廖允豌",
            "OfficialTime": "01:52:45",
            "RankAll": "3053",
            "NetTime": "01:49:25"
        },
        {
            "Bibnr": "35659",
            "Name": "陳朗星",
            "OfficialTime": "01:52:45",
            "RankAll": "3054",
            "NetTime": "01:47:17"
        },
        {
            "Bibnr": "20100",
            "Name": "邱怡君",
            "OfficialTime": "01:52:45",
            "RankAll": "3055",
            "NetTime": "01:51:50"
        },
        {
            "Bibnr": "32513",
            "Name": "廖明麟",
            "OfficialTime": "01:52:46",
            "RankAll": "3056",
            "NetTime": "01:51:31"
        },
        {
            "Bibnr": "24529",
            "Name": "吳季仲",
            "OfficialTime": "01:52:46",
            "RankAll": "3057",
            "NetTime": "01:49:05"
        },
        {
            "Bibnr": "32548",
            "Name": "張家豪",
            "OfficialTime": "01:52:46",
            "RankAll": "3058",
            "NetTime": "01:51:27"
        },
        {
            "Bibnr": "22588",
            "Name": "CHAN PIAN",
            "OfficialTime": "01:52:46",
            "RankAll": "3059",
            "NetTime": "01:49:21"
        },
        {
            "Bibnr": "18306",
            "Name": "尤筱涵",
            "OfficialTime": "01:52:46",
            "RankAll": "3060",
            "NetTime": "01:51:15"
        },
        {
            "Bibnr": "37001",
            "Name": "邱士豪",
            "OfficialTime": "01:52:47",
            "RankAll": "3061",
            "NetTime": "01:51:10"
        },
        {
            "Bibnr": "29465",
            "Name": "Choi kai chao",
            "OfficialTime": "01:52:47",
            "RankAll": "3062",
            "NetTime": "01:48:21"
        },
        {
            "Bibnr": "28135",
            "Name": "陳建中",
            "OfficialTime": "01:52:48",
            "RankAll": "3063",
            "NetTime": "01:50:33"
        },
        {
            "Bibnr": "33652",
            "Name": "Tang Ka Chun",
            "OfficialTime": "01:52:49",
            "RankAll": "3064",
            "NetTime": "01:50:11"
        },
        {
            "Bibnr": "27292",
            "Name": "林蔚儒",
            "OfficialTime": "01:52:49",
            "RankAll": "3065",
            "NetTime": "01:50:37"
        },
        {
            "Bibnr": "21319",
            "Name": "李筱書",
            "OfficialTime": "01:52:49",
            "RankAll": "3066",
            "NetTime": "01:50:27"
        },
        {
            "Bibnr": "26248",
            "Name": "莊薪益",
            "OfficialTime": "01:52:50",
            "RankAll": "3067",
            "NetTime": "01:49:14"
        },
        {
            "Bibnr": "34744",
            "Name": "張承富",
            "OfficialTime": "01:52:50",
            "RankAll": "3068",
            "NetTime": "01:50:07"
        },
        {
            "Bibnr": "24177",
            "Name": "林哲慶",
            "OfficialTime": "01:52:50",
            "RankAll": "3069",
            "NetTime": "01:45:34"
        },
        {
            "Bibnr": "26421",
            "Name": "陳宜鴻",
            "OfficialTime": "01:52:51",
            "RankAll": "3070",
            "NetTime": "01:52:19"
        },
        {
            "Bibnr": "30030",
            "Name": "林哲緯",
            "OfficialTime": "01:52:51",
            "RankAll": "3071",
            "NetTime": "01:44:22"
        },
        {
            "Bibnr": "32705",
            "Name": "吳宬紘",
            "OfficialTime": "01:52:52",
            "RankAll": "3072",
            "NetTime": "01:44:41"
        },
        {
            "Bibnr": "27076",
            "Name": "李書安",
            "OfficialTime": "01:52:52",
            "RankAll": "3073",
            "NetTime": "01:52:20"
        },
        {
            "Bibnr": "31130",
            "Name": "蔡永祥",
            "OfficialTime": "01:52:52",
            "RankAll": "3074",
            "NetTime": "01:50:53"
        },
        {
            "Bibnr": "25515",
            "Name": "陳信全",
            "OfficialTime": "01:52:52",
            "RankAll": "3075",
            "NetTime": "01:52:06"
        },
        {
            "Bibnr": "29444",
            "Name": "羅子閎",
            "OfficialTime": "01:52:52",
            "RankAll": "3076",
            "NetTime": "01:46:19"
        },
        {
            "Bibnr": "33212",
            "Name": "LI NGAR LUN ALAN",
            "OfficialTime": "01:52:52",
            "RankAll": "3077",
            "NetTime": "01:52:41"
        },
        {
            "Bibnr": "33395",
            "Name": "陳建明",
            "OfficialTime": "01:52:53",
            "RankAll": "3078",
            "NetTime": "01:51:28"
        },
        {
            "Bibnr": "30086",
            "Name": "王政忠",
            "OfficialTime": "01:52:53",
            "RankAll": "3079",
            "NetTime": "01:50:56"
        },
        {
            "Bibnr": "26719",
            "Name": "劉忠豪",
            "OfficialTime": "01:52:53",
            "RankAll": "3080",
            "NetTime": "01:51:41"
        },
        {
            "Bibnr": "21112",
            "Name": "俞可倩",
            "OfficialTime": "01:52:53",
            "RankAll": "3081",
            "NetTime": "01:52:29"
        },
        {
            "Bibnr": "22054",
            "Name": "王哲龍",
            "OfficialTime": "01:52:54",
            "RankAll": "3082",
            "NetTime": "01:50:33"
        },
        {
            "Bibnr": "37047",
            "Name": "施淙文",
            "OfficialTime": "01:52:54",
            "RankAll": "3083",
            "NetTime": "01:49:55"
        },
        {
            "Bibnr": "25032",
            "Name": "林振嘉",
            "OfficialTime": "01:52:54",
            "RankAll": "3084",
            "NetTime": "01:48:47"
        },
        {
            "Bibnr": "30242",
            "Name": "王開石",
            "OfficialTime": "01:52:55",
            "RankAll": "3085",
            "NetTime": "01:50:45"
        },
        {
            "Bibnr": "31425",
            "Name": "范瑋麟",
            "OfficialTime": "01:52:56",
            "RankAll": "3086",
            "NetTime": "01:49:03"
        },
        {
            "Bibnr": "34251",
            "Name": "巫奕宸",
            "OfficialTime": "01:52:56",
            "RankAll": "3087",
            "NetTime": "01:52:32"
        },
        {
            "Bibnr": "37467",
            "Name": "許袁僑",
            "OfficialTime": "01:52:56",
            "RankAll": "3088",
            "NetTime": "01:47:55"
        },
        {
            "Bibnr": "30298",
            "Name": "劉建宏",
            "OfficialTime": "01:52:56",
            "RankAll": "3089",
            "NetTime": "01:51:09"
        },
        {
            "Bibnr": "27689",
            "Name": "林威成",
            "OfficialTime": "01:52:56",
            "RankAll": "3090",
            "NetTime": "01:51:09"
        },
        {
            "Bibnr": "14581",
            "Name": "周庭辰",
            "OfficialTime": "01:52:57",
            "RankAll": "3091",
            "NetTime": "01:51:40"
        },
        {
            "Bibnr": "35400",
            "Name": "張偉文",
            "OfficialTime": "01:52:57",
            "RankAll": "3092",
            "NetTime": "01:49:25"
        },
        {
            "Bibnr": "20165",
            "Name": "張經艷",
            "OfficialTime": "01:52:58",
            "RankAll": "3093",
            "NetTime": "01:51:57"
        },
        {
            "Bibnr": "23233",
            "Name": "湯添雄",
            "OfficialTime": "01:52:59",
            "RankAll": "3094",
            "NetTime": "01:45:40"
        },
        {
            "Bibnr": "23407",
            "Name": "馮為龍",
            "OfficialTime": "01:53:00",
            "RankAll": "3095",
            "NetTime": "01:50:52"
        },
        {
            "Bibnr": "30563",
            "Name": "尤伯瑋",
            "OfficialTime": "01:53:00",
            "RankAll": "3096",
            "NetTime": "01:51:15"
        },
        {
            "Bibnr": "24489",
            "Name": "許哲嘉",
            "OfficialTime": "01:53:00",
            "RankAll": "3097",
            "NetTime": "01:50:22"
        },
        {
            "Bibnr": "26149",
            "Name": "康正德",
            "OfficialTime": "01:53:00",
            "RankAll": "3098",
            "NetTime": "01:51:47"
        },
        {
            "Bibnr": "37122",
            "Name": "吳武宏",
            "OfficialTime": "01:53:00",
            "RankAll": "3099",
            "NetTime": "01:48:21"
        },
        {
            "Bibnr": "26067",
            "Name": "簡承璋",
            "OfficialTime": "01:53:00",
            "RankAll": "3100",
            "NetTime": "01:52:38"
        },
        {
            "Bibnr": "19776",
            "Name": "魏詩宸",
            "OfficialTime": "01:53:00",
            "RankAll": "3101",
            "NetTime": "01:48:51"
        },
        {
            "Bibnr": "21655",
            "Name": "劉智財",
            "OfficialTime": "01:53:01",
            "RankAll": "3102",
            "NetTime": "01:52:07"
        },
        {
            "Bibnr": "14573",
            "Name": "陳昱儒",
            "OfficialTime": "01:53:01",
            "RankAll": "3103",
            "NetTime": "01:47:53"
        },
        {
            "Bibnr": "34763",
            "Name": "賴伯峻",
            "OfficialTime": "01:53:02",
            "RankAll": "3104",
            "NetTime": "01:49:50"
        },
        {
            "Bibnr": "37382",
            "Name": "曾建堯",
            "OfficialTime": "01:53:02",
            "RankAll": "3105",
            "NetTime": "01:51:03"
        },
        {
            "Bibnr": "14164",
            "Name": "陳芝妤",
            "OfficialTime": "01:53:03",
            "RankAll": "3106",
            "NetTime": "01:50:06"
        },
        {
            "Bibnr": "37123",
            "Name": "蕭家勝",
            "OfficialTime": "01:53:03",
            "RankAll": "3107",
            "NetTime": "01:51:55"
        },
        {
            "Bibnr": "37083",
            "Name": "楊鴻祥",
            "OfficialTime": "01:53:04",
            "RankAll": "3108",
            "NetTime": "01:52:45"
        },
        {
            "Bibnr": "27245",
            "Name": "陳暉豪",
            "OfficialTime": "01:53:05",
            "RankAll": "3109",
            "NetTime": "01:49:23"
        },
        {
            "Bibnr": "34773",
            "Name": "吳志鎮",
            "OfficialTime": "01:53:05",
            "RankAll": "3110",
            "NetTime": "01:50:19"
        },
        {
            "Bibnr": "25144",
            "Name": "陳畿叡",
            "OfficialTime": "01:53:06",
            "RankAll": "3111",
            "NetTime": "01:47:57"
        },
        {
            "Bibnr": "26767",
            "Name": "陳威宇",
            "OfficialTime": "01:53:08",
            "RankAll": "3112",
            "NetTime": "01:45:33"
        },
        {
            "Bibnr": "22248",
            "Name": "黃耀立",
            "OfficialTime": "01:53:09",
            "RankAll": "3113",
            "NetTime": "01:43:52"
        },
        {
            "Bibnr": "34635",
            "Name": "龔倫",
            "OfficialTime": "01:53:09",
            "RankAll": "3114",
            "NetTime": "01:45:26"
        },
        {
            "Bibnr": "31366",
            "Name": "Louis Vincent Edmond Boussekey",
            "OfficialTime": "01:53:09",
            "RankAll": "3115",
            "NetTime": "01:43:24"
        },
        {
            "Bibnr": "33693",
            "Name": "許庭維",
            "OfficialTime": "01:53:09",
            "RankAll": "3116",
            "NetTime": "01:46:27"
        },
        {
            "Bibnr": "33408",
            "Name": "陳鐸元",
            "OfficialTime": "01:53:09",
            "RankAll": "3117",
            "NetTime": "01:43:59"
        },
        {
            "Bibnr": "28384",
            "Name": "張宗凱",
            "OfficialTime": "01:53:09",
            "RankAll": "3118",
            "NetTime": "01:49:39"
        },
        {
            "Bibnr": "26793",
            "Name": "蕭憲徽",
            "OfficialTime": "01:53:09",
            "RankAll": "3119",
            "NetTime": "01:52:13"
        },
        {
            "Bibnr": "16100",
            "Name": "許庭瑄",
            "OfficialTime": "01:53:10",
            "RankAll": "3120",
            "NetTime": "01:52:49"
        },
        {
            "Bibnr": "16739",
            "Name": "張唯真",
            "OfficialTime": "01:53:10",
            "RankAll": "3121",
            "NetTime": "01:50:41"
        },
        {
            "Bibnr": "22743",
            "Name": "呂皇璋",
            "OfficialTime": "01:53:11",
            "RankAll": "3122",
            "NetTime": "01:52:55"
        },
        {
            "Bibnr": "32227",
            "Name": "何思賢",
            "OfficialTime": "01:53:11",
            "RankAll": "3123",
            "NetTime": "01:48:46"
        },
        {
            "Bibnr": "33574",
            "Name": "蔡耀廣",
            "OfficialTime": "01:53:11",
            "RankAll": "3124",
            "NetTime": "01:49:38"
        },
        {
            "Bibnr": "22499",
            "Name": "張中瀚",
            "OfficialTime": "01:53:11",
            "RankAll": "3125",
            "NetTime": "01:51:42"
        },
        {
            "Bibnr": "20391",
            "Name": "劉穎霖",
            "OfficialTime": "01:53:12",
            "RankAll": "3126",
            "NetTime": "01:49:33"
        },
        {
            "Bibnr": "15483",
            "Name": "CHEUNG LOCK YIU",
            "OfficialTime": "01:53:12",
            "RankAll": "3127",
            "NetTime": "01:49:33"
        },
        {
            "Bibnr": "14582",
            "Name": "黃品絜",
            "OfficialTime": "01:53:12",
            "RankAll": "3128",
            "NetTime": "01:52:03"
        },
        {
            "Bibnr": "15017",
            "Name": "林佩均",
            "OfficialTime": "01:53:12",
            "RankAll": "3129",
            "NetTime": "01:49:50"
        },
        {
            "Bibnr": "21299",
            "Name": "施絜中",
            "OfficialTime": "01:53:12",
            "RankAll": "3130",
            "NetTime": "01:52:03"
        },
        {
            "Bibnr": "19352",
            "Name": "王曉珊",
            "OfficialTime": "01:53:13",
            "RankAll": "3131",
            "NetTime": "01:52:54"
        },
        {
            "Bibnr": "29520",
            "Name": "蔡嘉航",
            "OfficialTime": "01:53:13",
            "RankAll": "3132",
            "NetTime": "01:51:15"
        },
        {
            "Bibnr": "35691",
            "Name": "鍾偉謙",
            "OfficialTime": "01:53:13",
            "RankAll": "3133",
            "NetTime": "01:52:13"
        },
        {
            "Bibnr": "22761",
            "Name": "詹翔宇",
            "OfficialTime": "01:53:13",
            "RankAll": "3134",
            "NetTime": "01:48:38"
        },
        {
            "Bibnr": "15052",
            "Name": "蕭沛芛",
            "OfficialTime": "01:53:14",
            "RankAll": "3135",
            "NetTime": "01:41:12"
        },
        {
            "Bibnr": "21498",
            "Name": "蔡詩芬",
            "OfficialTime": "01:53:15",
            "RankAll": "3136",
            "NetTime": "01:52:24"
        },
        {
            "Bibnr": "24558",
            "Name": "廖崇慶",
            "OfficialTime": "01:53:15",
            "RankAll": "3137",
            "NetTime": "01:52:42"
        },
        {
            "Bibnr": "29186",
            "Name": "包家瑞",
            "OfficialTime": "01:53:15",
            "RankAll": "3138",
            "NetTime": "01:43:54"
        },
        {
            "Bibnr": "25635",
            "Name": "孫中騏",
            "OfficialTime": "01:53:15",
            "RankAll": "3139",
            "NetTime": "01:46:23"
        },
        {
            "Bibnr": "24287",
            "Name": "蔡佳峰",
            "OfficialTime": "01:53:16",
            "RankAll": "3140",
            "NetTime": "01:49:41"
        },
        {
            "Bibnr": "36736",
            "Name": "郭國煒",
            "OfficialTime": "01:53:16",
            "RankAll": "3141",
            "NetTime": "01:51:31"
        },
        {
            "Bibnr": "29551",
            "Name": "楊和宗",
            "OfficialTime": "01:53:16",
            "RankAll": "3142",
            "NetTime": "01:46:39"
        },
        {
            "Bibnr": "36738",
            "Name": "譚錫澎",
            "OfficialTime": "01:53:16",
            "RankAll": "3143",
            "NetTime": "01:51:30"
        },
        {
            "Bibnr": "30046",
            "Name": "周欽華",
            "OfficialTime": "01:53:16",
            "RankAll": "3144",
            "NetTime": "01:41:55"
        },
        {
            "Bibnr": "24614",
            "Name": "Yiu Hon Leung",
            "OfficialTime": "01:53:16",
            "RankAll": "3145",
            "NetTime": "01:50:23"
        },
        {
            "Bibnr": "32586",
            "Name": "林宜螢",
            "OfficialTime": "01:53:17",
            "RankAll": "3146",
            "NetTime": "01:49:48"
        },
        {
            "Bibnr": "25538",
            "Name": "Kevin John O. Estillore",
            "OfficialTime": "01:53:17",
            "RankAll": "3147",
            "NetTime": "01:44:52"
        },
        {
            "Bibnr": "17691",
            "Name": "王顗熒",
            "OfficialTime": "01:53:17",
            "RankAll": "3148",
            "NetTime": "01:48:17"
        },
        {
            "Bibnr": "14238",
            "Name": "陳韻琦",
            "OfficialTime": "01:53:17",
            "RankAll": "3149",
            "NetTime": "01:50:13"
        },
        {
            "Bibnr": "33488",
            "Name": "劉冠毅",
            "OfficialTime": "01:53:17",
            "RankAll": "3150",
            "NetTime": "01:49:38"
        },
        {
            "Bibnr": "26462",
            "Name": "張友誠",
            "OfficialTime": "01:53:17",
            "RankAll": "3151",
            "NetTime": "01:50:11"
        },
        {
            "Bibnr": "32687",
            "Name": "NG SIU KWONG STANLEY",
            "OfficialTime": "01:53:18",
            "RankAll": "3152",
            "NetTime": "01:48:43"
        },
        {
            "Bibnr": "30649",
            "Name": "DGreat Brightwell",
            "OfficialTime": "01:53:18",
            "RankAll": "3153",
            "NetTime": "01:52:10"
        },
        {
            "Bibnr": "32268",
            "Name": "張君堯",
            "OfficialTime": "01:53:19",
            "RankAll": "3154",
            "NetTime": "01:46:47"
        },
        {
            "Bibnr": "31148",
            "Name": "江冠儒",
            "OfficialTime": "01:53:19",
            "RankAll": "3155",
            "NetTime": "01:52:12"
        },
        {
            "Bibnr": "27104",
            "Name": "王寵銘",
            "OfficialTime": "01:53:20",
            "RankAll": "3156",
            "NetTime": "01:49:53"
        },
        {
            "Bibnr": "22266",
            "Name": "黃增稊",
            "OfficialTime": "01:53:20",
            "RankAll": "3157",
            "NetTime": "01:49:59"
        },
        {
            "Bibnr": "23798",
            "Name": "林俊維",
            "OfficialTime": "01:53:20",
            "RankAll": "3158",
            "NetTime": "01:52:55"
        },
        {
            "Bibnr": "29457",
            "Name": "Ting Pong Gabriel Ho",
            "OfficialTime": "01:53:20",
            "RankAll": "3159",
            "NetTime": "01:48:29"
        },
        {
            "Bibnr": "36344",
            "Name": "陳彥均",
            "OfficialTime": "01:53:20",
            "RankAll": "3160",
            "NetTime": "01:48:49"
        },
        {
            "Bibnr": "23324",
            "Name": "李昱晨",
            "OfficialTime": "01:53:21",
            "RankAll": "3161",
            "NetTime": "01:51:04"
        },
        {
            "Bibnr": "35054",
            "Name": "陳冠諭",
            "OfficialTime": "01:53:21",
            "RankAll": "3162",
            "NetTime": "01:51:19"
        },
        {
            "Bibnr": "29479",
            "Name": "謝德全",
            "OfficialTime": "01:53:21",
            "RankAll": "3163",
            "NetTime": "01:52:33"
        },
        {
            "Bibnr": "23438",
            "Name": "Leung Man Chun",
            "OfficialTime": "01:53:21",
            "RankAll": "3164",
            "NetTime": "01:45:57"
        },
        {
            "Bibnr": "19761",
            "Name": "張雯婷",
            "OfficialTime": "01:53:22",
            "RankAll": "3165",
            "NetTime": "01:49:25"
        },
        {
            "Bibnr": "32632",
            "Name": "劉宣徹",
            "OfficialTime": "01:53:22",
            "RankAll": "3166",
            "NetTime": "01:49:25"
        },
        {
            "Bibnr": "30453",
            "Name": "魏士傑",
            "OfficialTime": "01:53:22",
            "RankAll": "3167",
            "NetTime": "01:52:05"
        },
        {
            "Bibnr": "26725",
            "Name": "劉寶華",
            "OfficialTime": "01:53:24",
            "RankAll": "3168",
            "NetTime": "01:50:11"
        },
        {
            "Bibnr": "26717",
            "Name": "黃伯元",
            "OfficialTime": "01:53:24",
            "RankAll": "3169",
            "NetTime": "01:50:09"
        },
        {
            "Bibnr": "24596",
            "Name": "李權霖",
            "OfficialTime": "01:53:25",
            "RankAll": "3170",
            "NetTime": "01:51:39"
        },
        {
            "Bibnr": "36603",
            "Name": "陳政嘉",
            "OfficialTime": "01:53:25",
            "RankAll": "3171",
            "NetTime": "01:53:25"
        },
        {
            "Bibnr": "33605",
            "Name": "董恩遠",
            "OfficialTime": "01:53:25",
            "RankAll": "3172",
            "NetTime": "01:50:41"
        },
        {
            "Bibnr": "31032",
            "Name": "梁志豪",
            "OfficialTime": "01:53:26",
            "RankAll": "3173",
            "NetTime": "01:52:52"
        },
        {
            "Bibnr": "19096",
            "Name": "楊雅惠",
            "OfficialTime": "01:53:26",
            "RankAll": "3174",
            "NetTime": "01:50:33"
        },
        {
            "Bibnr": "35124",
            "Name": "卓廷威",
            "OfficialTime": "01:53:26",
            "RankAll": "3175",
            "NetTime": "01:49:30"
        },
        {
            "Bibnr": "20090",
            "Name": "Mak Ka Yee",
            "OfficialTime": "01:53:26",
            "RankAll": "3176",
            "NetTime": "01:52:42"
        },
        {
            "Bibnr": "34796",
            "Name": "張鈞凱",
            "OfficialTime": "01:53:26",
            "RankAll": "3177",
            "NetTime": "01:51:59"
        },
        {
            "Bibnr": "22384",
            "Name": "陳玟銓",
            "OfficialTime": "01:53:26",
            "RankAll": "3178",
            "NetTime": "01:50:06"
        },
        {
            "Bibnr": "28211",
            "Name": "李榮智",
            "OfficialTime": "01:53:27",
            "RankAll": "3179",
            "NetTime": "01:53:05"
        },
        {
            "Bibnr": "37448",
            "Name": "王燕杰",
            "OfficialTime": "01:53:27",
            "RankAll": "3180",
            "NetTime": "01:51:29"
        },
        {
            "Bibnr": "14490",
            "Name": "鄭芬芳",
            "OfficialTime": "01:53:28",
            "RankAll": "3181",
            "NetTime": "01:50:19"
        },
        {
            "Bibnr": "28784",
            "Name": "大塚 崇?",
            "OfficialTime": "01:53:28",
            "RankAll": "3182",
            "NetTime": "01:50:20"
        },
        {
            "Bibnr": "30208",
            "Name": "陳思源",
            "OfficialTime": "01:53:29",
            "RankAll": "3183",
            "NetTime": "01:50:53"
        },
        {
            "Bibnr": "36160",
            "Name": "曾韋翰",
            "OfficialTime": "01:53:29",
            "RankAll": "3184",
            "NetTime": "01:47:21"
        },
        {
            "Bibnr": "35716",
            "Name": "劉家進",
            "OfficialTime": "01:53:29",
            "RankAll": "3185",
            "NetTime": "01:47:56"
        },
        {
            "Bibnr": "20291",
            "Name": "陳嘉郁",
            "OfficialTime": "01:53:29",
            "RankAll": "3186",
            "NetTime": "01:52:23"
        },
        {
            "Bibnr": "22374",
            "Name": "謝昌勝",
            "OfficialTime": "01:53:29",
            "RankAll": "3187",
            "NetTime": "01:48:38"
        },
        {
            "Bibnr": "31253",
            "Name": "朱杰",
            "OfficialTime": "01:53:30",
            "RankAll": "3188",
            "NetTime": "01:49:33"
        },
        {
            "Bibnr": "26355",
            "Name": "王謙和",
            "OfficialTime": "01:53:30",
            "RankAll": "3189",
            "NetTime": "01:49:56"
        },
        {
            "Bibnr": "29630",
            "Name": "TUNG LING NGAI",
            "OfficialTime": "01:53:30",
            "RankAll": "3190",
            "NetTime": "01:51:26"
        },
        {
            "Bibnr": "28527",
            "Name": "李忠孝",
            "OfficialTime": "01:53:31",
            "RankAll": "3191",
            "NetTime": "01:51:11"
        },
        {
            "Bibnr": "17030",
            "Name": "李嘉恩",
            "OfficialTime": "01:53:31",
            "RankAll": "3192",
            "NetTime": "01:51:11"
        },
        {
            "Bibnr": "36670",
            "Name": "楊昇峰",
            "OfficialTime": "01:53:31",
            "RankAll": "3193",
            "NetTime": "01:45:15"
        },
        {
            "Bibnr": "37003",
            "Name": "劉偉芳",
            "OfficialTime": "01:53:31",
            "RankAll": "3194",
            "NetTime": "01:49:11"
        },
        {
            "Bibnr": "24038",
            "Name": "林宜融",
            "OfficialTime": "01:53:32",
            "RankAll": "3195",
            "NetTime": "01:50:37"
        },
        {
            "Bibnr": "33218",
            "Name": "魏照軒",
            "OfficialTime": "01:53:33",
            "RankAll": "3196",
            "NetTime": "01:50:41"
        },
        {
            "Bibnr": "34200",
            "Name": "高志榮",
            "OfficialTime": "01:53:33",
            "RankAll": "3197",
            "NetTime": "01:51:56"
        },
        {
            "Bibnr": "36594",
            "Name": "陳淮任",
            "OfficialTime": "01:53:33",
            "RankAll": "3198",
            "NetTime": "01:50:12"
        },
        {
            "Bibnr": "27338",
            "Name": "鍾毅",
            "OfficialTime": "01:53:34",
            "RankAll": "3199",
            "NetTime": "01:52:00"
        },
        {
            "Bibnr": "23379",
            "Name": "林宏欣",
            "OfficialTime": "01:53:34",
            "RankAll": "3200",
            "NetTime": "01:49:41"
        },
        {
            "Bibnr": "22171",
            "Name": "羅仕峻",
            "OfficialTime": "01:53:36",
            "RankAll": "3201",
            "NetTime": "01:52:14"
        },
        {
            "Bibnr": "36108",
            "Name": "莊敬濱",
            "OfficialTime": "01:53:36",
            "RankAll": "3202",
            "NetTime": "01:49:37"
        },
        {
            "Bibnr": "23272",
            "Name": "李榮瑞",
            "OfficialTime": "01:53:36",
            "RankAll": "3203",
            "NetTime": "01:51:55"
        },
        {
            "Bibnr": "30736",
            "Name": "曾翊展",
            "OfficialTime": "01:53:37",
            "RankAll": "3204",
            "NetTime": "01:50:18"
        },
        {
            "Bibnr": "34305",
            "Name": "陳朝陽",
            "OfficialTime": "01:53:37",
            "RankAll": "3205",
            "NetTime": "01:44:31"
        },
        {
            "Bibnr": "33304",
            "Name": "王文鴻",
            "OfficialTime": "01:53:38",
            "RankAll": "3206",
            "NetTime": "01:50:07"
        },
        {
            "Bibnr": "19256",
            "Name": "Lee Ka Hau",
            "OfficialTime": "01:53:38",
            "RankAll": "3207",
            "NetTime": "01:45:19"
        },
        {
            "Bibnr": "26796",
            "Name": "盧啓聰",
            "OfficialTime": "01:53:38",
            "RankAll": "3208",
            "NetTime": "01:52:33"
        },
        {
            "Bibnr": "31537",
            "Name": "林鼎森",
            "OfficialTime": "01:53:39",
            "RankAll": "3209",
            "NetTime": "01:52:40"
        },
        {
            "Bibnr": "27603",
            "Name": "許瑍明",
            "OfficialTime": "01:53:39",
            "RankAll": "3210",
            "NetTime": "01:45:02"
        },
        {
            "Bibnr": "23130",
            "Name": "林墾",
            "OfficialTime": "01:53:39",
            "RankAll": "3211",
            "NetTime": "01:46:35"
        },
        {
            "Bibnr": "30655",
            "Name": "陳振ㄧ",
            "OfficialTime": "01:53:39",
            "RankAll": "3212",
            "NetTime": "01:52:20"
        },
        {
            "Bibnr": "31252",
            "Name": "蕭永政",
            "OfficialTime": "01:53:40",
            "RankAll": "3213",
            "NetTime": "01:50:44"
        },
        {
            "Bibnr": "28686",
            "Name": "温淵光",
            "OfficialTime": "01:53:40",
            "RankAll": "3214",
            "NetTime": "01:50:39"
        },
        {
            "Bibnr": "29756",
            "Name": "Chow Ting Yung",
            "OfficialTime": "01:53:40",
            "RankAll": "3215",
            "NetTime": "01:50:39"
        },
        {
            "Bibnr": "36545",
            "Name": "陳凱祥",
            "OfficialTime": "01:53:40",
            "RankAll": "3216",
            "NetTime": "01:47:39"
        },
        {
            "Bibnr": "35878",
            "Name": "FURUSAWA EIJI",
            "OfficialTime": "01:53:41",
            "RankAll": "3217",
            "NetTime": "01:45:26"
        },
        {
            "Bibnr": "24089",
            "Name": "蘇德軒",
            "OfficialTime": "01:53:41",
            "RankAll": "3218",
            "NetTime": "01:45:32"
        },
        {
            "Bibnr": "34369",
            "Name": "吳誌銘",
            "OfficialTime": "01:53:41",
            "RankAll": "3219",
            "NetTime": "01:51:58"
        },
        {
            "Bibnr": "21734",
            "Name": "王昱崴",
            "OfficialTime": "01:53:41",
            "RankAll": "3220",
            "NetTime": "01:52:26"
        },
        {
            "Bibnr": "35842",
            "Name": "SAITO SHINYA",
            "OfficialTime": "01:53:42",
            "RankAll": "3221",
            "NetTime": "01:43:32"
        },
        {
            "Bibnr": "28238",
            "Name": "周冠儒",
            "OfficialTime": "01:53:42",
            "RankAll": "3222",
            "NetTime": "01:49:27"
        },
        {
            "Bibnr": "25132",
            "Name": "黃文慶",
            "OfficialTime": "01:53:42",
            "RankAll": "3223",
            "NetTime": "01:46:33"
        },
        {
            "Bibnr": "23385",
            "Name": "蔡明宏",
            "OfficialTime": "01:53:42",
            "RankAll": "3224",
            "NetTime": "01:50:43"
        },
        {
            "Bibnr": "20245",
            "Name": "Leung Po Shan",
            "OfficialTime": "01:53:43",
            "RankAll": "3225",
            "NetTime": "01:52:35"
        },
        {
            "Bibnr": "22468",
            "Name": "陳廷濠",
            "OfficialTime": "01:53:43",
            "RankAll": "3226",
            "NetTime": "01:52:59"
        },
        {
            "Bibnr": "37373",
            "Name": "潘信汎",
            "OfficialTime": "01:53:44",
            "RankAll": "3227",
            "NetTime": "01:52:21"
        },
        {
            "Bibnr": "30082",
            "Name": "王緯裕",
            "OfficialTime": "01:53:44",
            "RankAll": "3228",
            "NetTime": "01:52:52"
        },
        {
            "Bibnr": "23271",
            "Name": "陳佳弘",
            "OfficialTime": "01:53:44",
            "RankAll": "3229",
            "NetTime": "01:53:15"
        },
        {
            "Bibnr": "28565",
            "Name": "張耀文",
            "OfficialTime": "01:53:44",
            "RankAll": "3230",
            "NetTime": "01:51:12"
        },
        {
            "Bibnr": "24284",
            "Name": "楊軒政",
            "OfficialTime": "01:53:45",
            "RankAll": "3231",
            "NetTime": "01:51:11"
        },
        {
            "Bibnr": "28284",
            "Name": "彭日平",
            "OfficialTime": "01:53:45",
            "RankAll": "3232",
            "NetTime": "01:51:01"
        },
        {
            "Bibnr": "25089",
            "Name": "吳宗翰",
            "OfficialTime": "01:53:45",
            "RankAll": "3233",
            "NetTime": "01:52:25"
        },
        {
            "Bibnr": "32228",
            "Name": "林鈺翔",
            "OfficialTime": "01:53:45",
            "RankAll": "3234",
            "NetTime": "01:46:03"
        },
        {
            "Bibnr": "28286",
            "Name": "黃文楷",
            "OfficialTime": "01:53:46",
            "RankAll": "3235",
            "NetTime": "01:47:31"
        },
        {
            "Bibnr": "27734",
            "Name": "許哲瑋",
            "OfficialTime": "01:53:46",
            "RankAll": "3236",
            "NetTime": "01:51:33"
        },
        {
            "Bibnr": "14605",
            "Name": "莊雅涵",
            "OfficialTime": "01:53:47",
            "RankAll": "3237",
            "NetTime": "01:52:17"
        },
        {
            "Bibnr": "37039",
            "Name": "陳冠希",
            "OfficialTime": "01:53:47",
            "RankAll": "3238",
            "NetTime": "01:52:06"
        },
        {
            "Bibnr": "20185",
            "Name": "林曉淇",
            "OfficialTime": "01:53:47",
            "RankAll": "3239",
            "NetTime": "01:51:26"
        },
        {
            "Bibnr": "30116",
            "Name": "羅儒豪",
            "OfficialTime": "01:53:48",
            "RankAll": "3240",
            "NetTime": "01:42:23"
        },
        {
            "Bibnr": "26653",
            "Name": "Zhang Guohui",
            "OfficialTime": "01:53:49",
            "RankAll": "3241",
            "NetTime": "01:44:23"
        },
        {
            "Bibnr": "30345",
            "Name": "陳建彬",
            "OfficialTime": "01:53:49",
            "RankAll": "3242",
            "NetTime": "01:52:36"
        },
        {
            "Bibnr": "27700",
            "Name": "鄒文軒",
            "OfficialTime": "01:53:49",
            "RankAll": "3243",
            "NetTime": "01:52:25"
        },
        {
            "Bibnr": "28755",
            "Name": "黃信修",
            "OfficialTime": "01:53:49",
            "RankAll": "3244",
            "NetTime": "01:53:29"
        },
        {
            "Bibnr": "34621",
            "Name": "林翔",
            "OfficialTime": "01:53:50",
            "RankAll": "3245",
            "NetTime": "01:49:55"
        },
        {
            "Bibnr": "28299",
            "Name": "黃銘偉",
            "OfficialTime": "01:53:50",
            "RankAll": "3246",
            "NetTime": "01:52:45"
        },
        {
            "Bibnr": "23302",
            "Name": "陳冠榮",
            "OfficialTime": "01:53:50",
            "RankAll": "3247",
            "NetTime": "01:51:48"
        },
        {
            "Bibnr": "20274",
            "Name": "董芳羽",
            "OfficialTime": "01:53:50",
            "RankAll": "3248",
            "NetTime": "01:52:38"
        },
        {
            "Bibnr": "37182",
            "Name": "陳志宇",
            "OfficialTime": "01:53:51",
            "RankAll": "3249",
            "NetTime": "01:50:06"
        },
        {
            "Bibnr": "15216",
            "Name": "黃喬暄",
            "OfficialTime": "01:53:52",
            "RankAll": "3250",
            "NetTime": "01:49:45"
        },
        {
            "Bibnr": "23273",
            "Name": "駱胤翰",
            "OfficialTime": "01:53:53",
            "RankAll": "3251",
            "NetTime": "01:52:52"
        },
        {
            "Bibnr": "20293",
            "Name": "Ng Lai Man",
            "OfficialTime": "01:53:53",
            "RankAll": "3252",
            "NetTime": "01:50:40"
        },
        {
            "Bibnr": "28750",
            "Name": "郭力緯",
            "OfficialTime": "01:53:53",
            "RankAll": "3253",
            "NetTime": "01:51:21"
        },
        {
            "Bibnr": "33451",
            "Name": "洪正",
            "OfficialTime": "01:53:54",
            "RankAll": "3254",
            "NetTime": "01:42:46"
        },
        {
            "Bibnr": "24304",
            "Name": "Chan Hei Yeung",
            "OfficialTime": "01:53:54",
            "RankAll": "3255",
            "NetTime": "01:50:07"
        },
        {
            "Bibnr": "34437",
            "Name": "柯凱甯",
            "OfficialTime": "01:53:55",
            "RankAll": "3256",
            "NetTime": "01:53:41"
        },
        {
            "Bibnr": "33239",
            "Name": "蔡政谷",
            "OfficialTime": "01:53:55",
            "RankAll": "3257",
            "NetTime": "01:45:20"
        },
        {
            "Bibnr": "29671",
            "Name": "廖茂峰",
            "OfficialTime": "01:53:56",
            "RankAll": "3258",
            "NetTime": "01:52:40"
        },
        {
            "Bibnr": "31497",
            "Name": "HO King Chuen",
            "OfficialTime": "01:53:56",
            "RankAll": "3259",
            "NetTime": "01:50:37"
        },
        {
            "Bibnr": "37112",
            "Name": "何文翔",
            "OfficialTime": "01:53:56",
            "RankAll": "3260",
            "NetTime": "01:50:30"
        },
        {
            "Bibnr": "26239",
            "Name": "何建霖",
            "OfficialTime": "01:53:56",
            "RankAll": "3261",
            "NetTime": "01:53:20"
        },
        {
            "Bibnr": "26585",
            "Name": "林晉央",
            "OfficialTime": "01:53:57",
            "RankAll": "3262",
            "NetTime": "01:49:56"
        },
        {
            "Bibnr": "35896",
            "Name": "TAKARAGI MASAKI",
            "OfficialTime": "01:53:57",
            "RankAll": "3263",
            "NetTime": "01:50:28"
        },
        {
            "Bibnr": "20667",
            "Name": "戴樂希",
            "OfficialTime": "01:53:58",
            "RankAll": "3264",
            "NetTime": "01:52:24"
        },
        {
            "Bibnr": "20462",
            "Name": "姜艷嫺",
            "OfficialTime": "01:53:58",
            "RankAll": "3265",
            "NetTime": "01:52:15"
        },
        {
            "Bibnr": "27372",
            "Name": "傅室宸",
            "OfficialTime": "01:53:58",
            "RankAll": "3266",
            "NetTime": "01:52:07"
        },
        {
            "Bibnr": "20739",
            "Name": "林樂寶",
            "OfficialTime": "01:53:59",
            "RankAll": "3267",
            "NetTime": "01:53:33"
        },
        {
            "Bibnr": "29306",
            "Name": "陳芖安",
            "OfficialTime": "01:53:59",
            "RankAll": "3268",
            "NetTime": "01:51:49"
        },
        {
            "Bibnr": "33065",
            "Name": "鄭筠諺",
            "OfficialTime": "01:53:59",
            "RankAll": "3269",
            "NetTime": "01:51:50"
        },
        {
            "Bibnr": "25151",
            "Name": "賴重睿",
            "OfficialTime": "01:54:00",
            "RankAll": "3270",
            "NetTime": "01:50:29"
        },
        {
            "Bibnr": "28319",
            "Name": "吳尚毅",
            "OfficialTime": "01:54:00",
            "RankAll": "3271",
            "NetTime": "01:51:01"
        },
        {
            "Bibnr": "26323",
            "Name": "廖育賢",
            "OfficialTime": "01:54:00",
            "RankAll": "3272",
            "NetTime": "01:52:51"
        },
        {
            "Bibnr": "25651",
            "Name": "謝允正",
            "OfficialTime": "01:54:02",
            "RankAll": "3273",
            "NetTime": "01:45:00"
        },
        {
            "Bibnr": "25179",
            "Name": "陳昱嘉",
            "OfficialTime": "01:54:02",
            "RankAll": "3274",
            "NetTime": "01:50:20"
        },
        {
            "Bibnr": "21364",
            "Name": "陳靖旻",
            "OfficialTime": "01:54:03",
            "RankAll": "3275",
            "NetTime": "01:52:29"
        },
        {
            "Bibnr": "33403",
            "Name": "譚至良",
            "OfficialTime": "01:54:03",
            "RankAll": "3276",
            "NetTime": "01:46:00"
        },
        {
            "Bibnr": "32279",
            "Name": "許家豪",
            "OfficialTime": "01:54:03",
            "RankAll": "3277",
            "NetTime": "01:51:50"
        },
        {
            "Bibnr": "26138",
            "Name": "蔡承勳",
            "OfficialTime": "01:54:04",
            "RankAll": "3278",
            "NetTime": "01:52:54"
        },
        {
            "Bibnr": "25159",
            "Name": "王宗楠",
            "OfficialTime": "01:54:05",
            "RankAll": "3279",
            "NetTime": "01:47:28"
        },
        {
            "Bibnr": "25101",
            "Name": "胡新南",
            "OfficialTime": "01:54:05",
            "RankAll": "3280",
            "NetTime": "01:49:46"
        },
        {
            "Bibnr": "27697",
            "Name": "許國忠",
            "OfficialTime": "01:54:05",
            "RankAll": "3281",
            "NetTime": "01:53:13"
        },
        {
            "Bibnr": "21193",
            "Name": "陳婷芳",
            "OfficialTime": "01:54:06",
            "RankAll": "3282",
            "NetTime": "01:51:39"
        },
        {
            "Bibnr": "28682",
            "Name": "李健宗",
            "OfficialTime": "01:54:06",
            "RankAll": "3283",
            "NetTime": "01:50:19"
        },
        {
            "Bibnr": "22117",
            "Name": "林子翔",
            "OfficialTime": "01:54:07",
            "RankAll": "3284",
            "NetTime": "01:46:31"
        },
        {
            "Bibnr": "24660",
            "Name": "林岳樺",
            "OfficialTime": "01:54:07",
            "RankAll": "3285",
            "NetTime": "01:48:31"
        },
        {
            "Bibnr": "20777",
            "Name": "管美蓮",
            "OfficialTime": "01:54:07",
            "RankAll": "3286",
            "NetTime": "01:51:20"
        },
        {
            "Bibnr": "23393",
            "Name": "張家誠",
            "OfficialTime": "01:54:07",
            "RankAll": "3287",
            "NetTime": "01:50:44"
        },
        {
            "Bibnr": "29549",
            "Name": "張威凱",
            "OfficialTime": "01:54:07",
            "RankAll": "3288",
            "NetTime": "01:50:51"
        },
        {
            "Bibnr": "25737",
            "Name": "林藝哲",
            "OfficialTime": "01:54:08",
            "RankAll": "3289",
            "NetTime": "01:47:44"
        },
        {
            "Bibnr": "29159",
            "Name": "盧憲勳",
            "OfficialTime": "01:54:08",
            "RankAll": "3290",
            "NetTime": "01:52:57"
        },
        {
            "Bibnr": "26256",
            "Name": "蘇桂樟",
            "OfficialTime": "01:54:08",
            "RankAll": "3291",
            "NetTime": "01:51:46"
        },
        {
            "Bibnr": "26166",
            "Name": "王旭凱",
            "OfficialTime": "01:54:08",
            "RankAll": "3292",
            "NetTime": "01:54:00"
        },
        {
            "Bibnr": "37510",
            "Name": "黃啟魁",
            "OfficialTime": "01:54:08",
            "RankAll": "3293",
            "NetTime": "01:53:22"
        },
        {
            "Bibnr": "18633",
            "Name": "簡培雯",
            "OfficialTime": "01:54:09",
            "RankAll": "3294",
            "NetTime": "01:45:28"
        },
        {
            "Bibnr": "27436",
            "Name": "潘昌豪",
            "OfficialTime": "01:54:09",
            "RankAll": "3295",
            "NetTime": "01:43:25"
        },
        {
            "Bibnr": "21688",
            "Name": "曾銘鐘",
            "OfficialTime": "01:54:09",
            "RankAll": "3296",
            "NetTime": "01:49:01"
        },
        {
            "Bibnr": "15225",
            "Name": "楊惇安",
            "OfficialTime": "01:54:09",
            "RankAll": "3297",
            "NetTime": "01:51:57"
        },
        {
            "Bibnr": "18299",
            "Name": "陳雅婷",
            "OfficialTime": "01:54:10",
            "RankAll": "3298",
            "NetTime": "01:51:21"
        },
        {
            "Bibnr": "15725",
            "Name": "溫力穎",
            "OfficialTime": "01:54:10",
            "RankAll": "3299",
            "NetTime": "01:50:58"
        },
        {
            "Bibnr": "36896",
            "Name": "陳傑民",
            "OfficialTime": "01:54:11",
            "RankAll": "3300",
            "NetTime": "01:48:30"
        },
        {
            "Bibnr": "19610",
            "Name": "蔡幸憓",
            "OfficialTime": "01:54:11",
            "RankAll": "3301",
            "NetTime": "01:53:22"
        },
        {
            "Bibnr": "26638",
            "Name": "林祐綸",
            "OfficialTime": "01:54:11",
            "RankAll": "3302",
            "NetTime": "01:48:33"
        },
        {
            "Bibnr": "22223",
            "Name": "林楷儒",
            "OfficialTime": "01:54:12",
            "RankAll": "3303",
            "NetTime": "01:50:37"
        },
        {
            "Bibnr": "19695",
            "Name": "何佩珊",
            "OfficialTime": "01:54:12",
            "RankAll": "3304",
            "NetTime": "01:52:06"
        },
        {
            "Bibnr": "22669",
            "Name": "NG YIOW CHUAN",
            "OfficialTime": "01:54:13",
            "RankAll": "3305",
            "NetTime": "01:47:55"
        },
        {
            "Bibnr": "24227",
            "Name": "劉建忠",
            "OfficialTime": "01:54:14",
            "RankAll": "3306",
            "NetTime": "01:52:39"
        },
        {
            "Bibnr": "28659",
            "Name": "張敏倫",
            "OfficialTime": "01:54:15",
            "RankAll": "3307",
            "NetTime": "01:52:14"
        },
        {
            "Bibnr": "37290",
            "Name": "薛旻原",
            "OfficialTime": "01:54:15",
            "RankAll": "3308",
            "NetTime": "01:54:05"
        },
        {
            "Bibnr": "28323",
            "Name": "劉建宏",
            "OfficialTime": "01:54:15",
            "RankAll": "3309",
            "NetTime": "01:51:39"
        },
        {
            "Bibnr": "24079",
            "Name": "饒九庸",
            "OfficialTime": "01:54:15",
            "RankAll": "3310",
            "NetTime": "01:46:50"
        },
        {
            "Bibnr": "33337",
            "Name": "潘正良",
            "OfficialTime": "01:54:15",
            "RankAll": "3311",
            "NetTime": "01:51:04"
        },
        {
            "Bibnr": "27537",
            "Name": "黃稟紘",
            "OfficialTime": "01:54:16",
            "RankAll": "3312",
            "NetTime": "01:52:57"
        },
        {
            "Bibnr": "20757",
            "Name": "DEAN DEAN NG",
            "OfficialTime": "01:54:16",
            "RankAll": "3313",
            "NetTime": "01:54:14"
        },
        {
            "Bibnr": "23277",
            "Name": "林柏均",
            "OfficialTime": "01:54:17",
            "RankAll": "3314",
            "NetTime": "01:46:25"
        },
        {
            "Bibnr": "35724",
            "Name": "黃照安",
            "OfficialTime": "01:54:17",
            "RankAll": "3315",
            "NetTime": "01:50:21"
        },
        {
            "Bibnr": "26404",
            "Name": "鄭士魁",
            "OfficialTime": "01:54:17",
            "RankAll": "3316",
            "NetTime": "01:49:43"
        },
        {
            "Bibnr": "26069",
            "Name": "王柄豪",
            "OfficialTime": "01:54:19",
            "RankAll": "3317",
            "NetTime": "01:51:09"
        },
        {
            "Bibnr": "36893",
            "Name": "邢志恒",
            "OfficialTime": "01:54:19",
            "RankAll": "3318",
            "NetTime": "01:53:57"
        },
        {
            "Bibnr": "35866",
            "Name": "SANUGA YOSHIKUNI",
            "OfficialTime": "01:54:20",
            "RankAll": "3319",
            "NetTime": "01:49:20"
        },
        {
            "Bibnr": "34647",
            "Name": "張俊堯",
            "OfficialTime": "01:54:20",
            "RankAll": "3320",
            "NetTime": "01:53:17"
        },
        {
            "Bibnr": "29180",
            "Name": "林鼎翔",
            "OfficialTime": "01:54:20",
            "RankAll": "3321",
            "NetTime": "01:52:06"
        },
        {
            "Bibnr": "18637",
            "Name": "盧苔芬",
            "OfficialTime": "01:54:20",
            "RankAll": "3322",
            "NetTime": "01:50:08"
        },
        {
            "Bibnr": "37095",
            "Name": "陳宗偉",
            "OfficialTime": "01:54:20",
            "RankAll": "3323",
            "NetTime": "01:49:13"
        },
        {
            "Bibnr": "31796",
            "Name": "廖經亞",
            "OfficialTime": "01:54:20",
            "RankAll": "3324",
            "NetTime": "01:52:27"
        },
        {
            "Bibnr": "29492",
            "Name": "丁彥夫",
            "OfficialTime": "01:54:21",
            "RankAll": "3325",
            "NetTime": "01:52:01"
        },
        {
            "Bibnr": "26437",
            "Name": "徐世杰",
            "OfficialTime": "01:54:21",
            "RankAll": "3326",
            "NetTime": "01:53:51"
        },
        {
            "Bibnr": "29255",
            "Name": "李昀叡",
            "OfficialTime": "01:54:21",
            "RankAll": "3327",
            "NetTime": "01:51:23"
        },
        {
            "Bibnr": "16219",
            "Name": "曹喻涵",
            "OfficialTime": "01:54:21",
            "RankAll": "3328",
            "NetTime": "01:53:51"
        },
        {
            "Bibnr": "22142",
            "Name": "周建良",
            "OfficialTime": "01:54:22",
            "RankAll": "3329",
            "NetTime": "01:53:21"
        },
        {
            "Bibnr": "28729",
            "Name": "石政傑",
            "OfficialTime": "01:54:22",
            "RankAll": "3330",
            "NetTime": "01:50:59"
        },
        {
            "Bibnr": "15592",
            "Name": "黃姿熹",
            "OfficialTime": "01:54:22",
            "RankAll": "3331",
            "NetTime": "01:53:36"
        },
        {
            "Bibnr": "16211",
            "Name": "Ching In Yan",
            "OfficialTime": "01:54:23",
            "RankAll": "3332",
            "NetTime": "01:53:06"
        },
        {
            "Bibnr": "34119",
            "Name": "許箸驊",
            "OfficialTime": "01:54:23",
            "RankAll": "3333",
            "NetTime": "01:51:55"
        },
        {
            "Bibnr": "28078",
            "Name": "何瑞杰",
            "OfficialTime": "01:54:24",
            "RankAll": "3334",
            "NetTime": "01:45:00"
        },
        {
            "Bibnr": "20225",
            "Name": "蕭清華",
            "OfficialTime": "01:54:24",
            "RankAll": "3335",
            "NetTime": "01:51:16"
        },
        {
            "Bibnr": "29581",
            "Name": "周世昌",
            "OfficialTime": "01:54:24",
            "RankAll": "3336",
            "NetTime": "01:52:05"
        },
        {
            "Bibnr": "26088",
            "Name": "吳鴻偉",
            "OfficialTime": "01:54:25",
            "RankAll": "3337",
            "NetTime": "01:53:19"
        },
        {
            "Bibnr": "21784",
            "Name": "吳聲宗",
            "OfficialTime": "01:54:25",
            "RankAll": "3338",
            "NetTime": "01:54:15"
        },
        {
            "Bibnr": "32080",
            "Name": "刁茂盟",
            "OfficialTime": "01:54:25",
            "RankAll": "3339",
            "NetTime": "01:54:05"
        },
        {
            "Bibnr": "20045",
            "Name": "Lo Pui Shan",
            "OfficialTime": "01:54:26",
            "RankAll": "3340",
            "NetTime": "01:51:57"
        },
        {
            "Bibnr": "23145",
            "Name": "Chan Chak Kit",
            "OfficialTime": "01:54:26",
            "RankAll": "3341",
            "NetTime": "01:44:50"
        },
        {
            "Bibnr": "29199",
            "Name": "周文啓",
            "OfficialTime": "01:54:26",
            "RankAll": "3342",
            "NetTime": "01:52:52"
        },
        {
            "Bibnr": "26619",
            "Name": "張景皓",
            "OfficialTime": "01:54:27",
            "RankAll": "3343",
            "NetTime": "01:53:52"
        },
        {
            "Bibnr": "34683",
            "Name": "王治凱",
            "OfficialTime": "01:54:27",
            "RankAll": "3344",
            "NetTime": "01:52:38"
        },
        {
            "Bibnr": "15491",
            "Name": "黃素盈",
            "OfficialTime": "01:54:28",
            "RankAll": "3345",
            "NetTime": "01:53:51"
        },
        {
            "Bibnr": "33066",
            "Name": "劉郁政",
            "OfficialTime": "01:54:29",
            "RankAll": "3346",
            "NetTime": "01:50:17"
        },
        {
            "Bibnr": "23380",
            "Name": "張釗銘",
            "OfficialTime": "01:54:29",
            "RankAll": "3347",
            "NetTime": "01:53:01"
        },
        {
            "Bibnr": "34105",
            "Name": "王政皓",
            "OfficialTime": "01:54:29",
            "RankAll": "3348",
            "NetTime": "01:54:07"
        },
        {
            "Bibnr": "34791",
            "Name": "劉宗豪",
            "OfficialTime": "01:54:30",
            "RankAll": "3349",
            "NetTime": "01:51:44"
        },
        {
            "Bibnr": "30277",
            "Name": "TAI LING CHUAN",
            "OfficialTime": "01:54:30",
            "RankAll": "3350",
            "NetTime": "01:46:59"
        },
        {
            "Bibnr": "17744",
            "Name": "Tse sin yu",
            "OfficialTime": "01:54:30",
            "RankAll": "3351",
            "NetTime": "01:52:02"
        },
        {
            "Bibnr": "22307",
            "Name": "陳昱勝",
            "OfficialTime": "01:54:31",
            "RankAll": "3352",
            "NetTime": "01:51:38"
        },
        {
            "Bibnr": "26535",
            "Name": "廖于誠",
            "OfficialTime": "01:54:31",
            "RankAll": "3353",
            "NetTime": "01:54:11"
        },
        {
            "Bibnr": "32665",
            "Name": "HOMHYOUMGGI",
            "OfficialTime": "01:54:31",
            "RankAll": "3354",
            "NetTime": "01:48:10"
        },
        {
            "Bibnr": "28042",
            "Name": "范發智",
            "OfficialTime": "01:54:32",
            "RankAll": "3355",
            "NetTime": "01:44:26"
        },
        {
            "Bibnr": "28513",
            "Name": "劉地旺",
            "OfficialTime": "01:54:33",
            "RankAll": "3356",
            "NetTime": "01:53:48"
        },
        {
            "Bibnr": "15015",
            "Name": "林庭羽",
            "OfficialTime": "01:54:33",
            "RankAll": "3357",
            "NetTime": "01:49:00"
        },
        {
            "Bibnr": "26334",
            "Name": "LAU Pak-fai",
            "OfficialTime": "01:54:33",
            "RankAll": "3358",
            "NetTime": "01:54:17"
        },
        {
            "Bibnr": "32189",
            "Name": "侯鈞元",
            "OfficialTime": "01:54:33",
            "RankAll": "3359",
            "NetTime": "01:47:23"
        },
        {
            "Bibnr": "21737",
            "Name": "駱文華",
            "OfficialTime": "01:54:33",
            "RankAll": "3360",
            "NetTime": "01:43:18"
        },
        {
            "Bibnr": "16304",
            "Name": "黃佳茹",
            "OfficialTime": "01:54:33",
            "RankAll": "3361",
            "NetTime": "01:53:27"
        },
        {
            "Bibnr": "35823",
            "Name": "吳卓基",
            "OfficialTime": "01:54:34",
            "RankAll": "3362",
            "NetTime": "01:44:26"
        },
        {
            "Bibnr": "37334",
            "Name": "郭庭瑞",
            "OfficialTime": "01:54:34",
            "RankAll": "3363",
            "NetTime": "01:52:36"
        },
        {
            "Bibnr": "21637",
            "Name": "吳柏翰",
            "OfficialTime": "01:54:34",
            "RankAll": "3364",
            "NetTime": "01:53:51"
        },
        {
            "Bibnr": "22023",
            "Name": "陳佑軒",
            "OfficialTime": "01:54:35",
            "RankAll": "3365",
            "NetTime": "01:52:11"
        },
        {
            "Bibnr": "37276",
            "Name": "林德成",
            "OfficialTime": "01:54:36",
            "RankAll": "3366",
            "NetTime": "01:50:24"
        },
        {
            "Bibnr": "37215",
            "Name": "黃冠樺",
            "OfficialTime": "01:54:36",
            "RankAll": "3367",
            "NetTime": "01:53:54"
        },
        {
            "Bibnr": "35224",
            "Name": "朱峻廷",
            "OfficialTime": "01:54:37",
            "RankAll": "3368",
            "NetTime": "01:52:45"
        },
        {
            "Bibnr": "25174",
            "Name": "蔡昀助",
            "OfficialTime": "01:54:37",
            "RankAll": "3369",
            "NetTime": "01:50:54"
        },
        {
            "Bibnr": "15493",
            "Name": "SIO HIO WA",
            "OfficialTime": "01:54:38",
            "RankAll": "3370",
            "NetTime": "01:51:26"
        },
        {
            "Bibnr": "20085",
            "Name": "朱韻婷",
            "OfficialTime": "01:54:38",
            "RankAll": "3371",
            "NetTime": "01:53:56"
        },
        {
            "Bibnr": "28058",
            "Name": "謝明樺",
            "OfficialTime": "01:54:38",
            "RankAll": "3372",
            "NetTime": "01:52:24"
        },
        {
            "Bibnr": "16158",
            "Name": "劉姿辰",
            "OfficialTime": "01:54:39",
            "RankAll": "3373",
            "NetTime": "01:50:32"
        },
        {
            "Bibnr": "30187",
            "Name": "張惟亦",
            "OfficialTime": "01:54:39",
            "RankAll": "3374",
            "NetTime": "01:51:26"
        },
        {
            "Bibnr": "22192",
            "Name": "林宗源",
            "OfficialTime": "01:54:39",
            "RankAll": "3375",
            "NetTime": "01:50:21"
        },
        {
            "Bibnr": "23261",
            "Name": "林佳慶",
            "OfficialTime": "01:54:39",
            "RankAll": "3376",
            "NetTime": "01:49:27"
        },
        {
            "Bibnr": "31142",
            "Name": "李韋慶",
            "OfficialTime": "01:54:40",
            "RankAll": "3377",
            "NetTime": "01:48:33"
        },
        {
            "Bibnr": "20357",
            "Name": "馮楚雯",
            "OfficialTime": "01:54:40",
            "RankAll": "3378",
            "NetTime": "01:53:36"
        },
        {
            "Bibnr": "28533",
            "Name": "Chu kai wing",
            "OfficialTime": "01:54:40",
            "RankAll": "3379",
            "NetTime": "01:49:07"
        },
        {
            "Bibnr": "32388",
            "Name": "呂岳展",
            "OfficialTime": "01:54:40",
            "RankAll": "3380",
            "NetTime": "01:50:36"
        },
        {
            "Bibnr": "23702",
            "Name": "黃瑞亮",
            "OfficialTime": "01:54:41",
            "RankAll": "3381",
            "NetTime": "01:54:25"
        },
        {
            "Bibnr": "28674",
            "Name": "李睿杰",
            "OfficialTime": "01:54:41",
            "RankAll": "3382",
            "NetTime": "01:52:28"
        },
        {
            "Bibnr": "25292",
            "Name": "周益年",
            "OfficialTime": "01:54:42",
            "RankAll": "3383",
            "NetTime": "01:50:39"
        },
        {
            "Bibnr": "20254",
            "Name": "莊佩雯",
            "OfficialTime": "01:54:42",
            "RankAll": "3384",
            "NetTime": "01:54:32"
        },
        {
            "Bibnr": "35769",
            "Name": "黃劍峯",
            "OfficialTime": "01:54:42",
            "RankAll": "3385",
            "NetTime": "01:48:23"
        },
        {
            "Bibnr": "27036",
            "Name": "廖笖成",
            "OfficialTime": "01:54:42",
            "RankAll": "3386",
            "NetTime": "01:52:03"
        },
        {
            "Bibnr": "22281",
            "Name": "陳嘉政",
            "OfficialTime": "01:54:42",
            "RankAll": "3387",
            "NetTime": "01:52:19"
        },
        {
            "Bibnr": "17258",
            "Name": "張家華",
            "OfficialTime": "01:54:42",
            "RankAll": "3388",
            "NetTime": "01:52:15"
        },
        {
            "Bibnr": "16154",
            "Name": "林慧欣",
            "OfficialTime": "01:54:43",
            "RankAll": "3389",
            "NetTime": "01:52:41"
        },
        {
            "Bibnr": "34390",
            "Name": "田珷鈞",
            "OfficialTime": "01:54:44",
            "RankAll": "3390",
            "NetTime": "01:50:57"
        },
        {
            "Bibnr": "20214",
            "Name": "曾玲芳",
            "OfficialTime": "01:54:45",
            "RankAll": "3391",
            "NetTime": "01:53:56"
        },
        {
            "Bibnr": "37062",
            "Name": "許躍騰",
            "OfficialTime": "01:54:45",
            "RankAll": "3392",
            "NetTime": "01:52:31"
        },
        {
            "Bibnr": "31665",
            "Name": "林岳震",
            "OfficialTime": "01:54:46",
            "RankAll": "3393",
            "NetTime": "01:53:40"
        },
        {
            "Bibnr": "24023",
            "Name": "楊覲榘",
            "OfficialTime": "01:54:46",
            "RankAll": "3394",
            "NetTime": "01:51:23"
        },
        {
            "Bibnr": "24535",
            "Name": "廖建豪",
            "OfficialTime": "01:54:47",
            "RankAll": "3395",
            "NetTime": "01:53:48"
        },
        {
            "Bibnr": "34269",
            "Name": "王炳堯",
            "OfficialTime": "01:54:47",
            "RankAll": "3396",
            "NetTime": "01:51:47"
        },
        {
            "Bibnr": "24348",
            "Name": "許國昌",
            "OfficialTime": "01:54:47",
            "RankAll": "3397",
            "NetTime": "01:51:21"
        },
        {
            "Bibnr": "15423",
            "Name": "郭語璇",
            "OfficialTime": "01:54:47",
            "RankAll": "3398",
            "NetTime": "01:53:18"
        },
        {
            "Bibnr": "34221",
            "Name": "潘祥瑞",
            "OfficialTime": "01:54:48",
            "RankAll": "3399",
            "NetTime": "01:53:18"
        },
        {
            "Bibnr": "35015",
            "Name": "李惠寧",
            "OfficialTime": "01:54:48",
            "RankAll": "3400",
            "NetTime": "01:50:21"
        },
        {
            "Bibnr": "30480",
            "Name": "廖辰恩",
            "OfficialTime": "01:54:48",
            "RankAll": "3401",
            "NetTime": "01:46:54"
        },
        {
            "Bibnr": "25660",
            "Name": "鄭翔澧",
            "OfficialTime": "01:54:48",
            "RankAll": "3402",
            "NetTime": "01:53:50"
        },
        {
            "Bibnr": "18365",
            "Name": "徐新雅",
            "OfficialTime": "01:54:49",
            "RankAll": "3403",
            "NetTime": "01:53:22"
        },
        {
            "Bibnr": "37424",
            "Name": "謝瑋哲",
            "OfficialTime": "01:54:49",
            "RankAll": "3404",
            "NetTime": "01:54:24"
        },
        {
            "Bibnr": "30381",
            "Name": "吳炯廷",
            "OfficialTime": "01:54:49",
            "RankAll": "3405",
            "NetTime": "01:52:18"
        },
        {
            "Bibnr": "31654",
            "Name": "葉懿賢",
            "OfficialTime": "01:54:49",
            "RankAll": "3406",
            "NetTime": "01:53:21"
        },
        {
            "Bibnr": "26358",
            "Name": "莊學康",
            "OfficialTime": "01:54:50",
            "RankAll": "3407",
            "NetTime": "01:51:23"
        },
        {
            "Bibnr": "20485",
            "Name": "李惠賢",
            "OfficialTime": "01:54:50",
            "RankAll": "3408",
            "NetTime": "01:49:56"
        },
        {
            "Bibnr": "36284",
            "Name": "潘柏元",
            "OfficialTime": "01:54:51",
            "RankAll": "3409",
            "NetTime": "01:50:05"
        },
        {
            "Bibnr": "33646",
            "Name": "吳育能",
            "OfficialTime": "01:54:51",
            "RankAll": "3410",
            "NetTime": "01:48:55"
        },
        {
            "Bibnr": "24184",
            "Name": "周冠霖",
            "OfficialTime": "01:54:51",
            "RankAll": "3411",
            "NetTime": "01:44:33"
        },
        {
            "Bibnr": "22129",
            "Name": "鄭偉明",
            "OfficialTime": "01:54:51",
            "RankAll": "3412",
            "NetTime": "01:53:28"
        },
        {
            "Bibnr": "33525",
            "Name": "林義評",
            "OfficialTime": "01:54:52",
            "RankAll": "3413",
            "NetTime": "01:54:30"
        },
        {
            "Bibnr": "28713",
            "Name": "江昱昌",
            "OfficialTime": "01:54:52",
            "RankAll": "3414",
            "NetTime": "01:48:04"
        },
        {
            "Bibnr": "20099",
            "Name": "陳佳潔",
            "OfficialTime": "01:54:52",
            "RankAll": "3415",
            "NetTime": "01:54:26"
        },
        {
            "Bibnr": "14441",
            "Name": "陳佳鈴",
            "OfficialTime": "01:54:52",
            "RankAll": "3416",
            "NetTime": "01:53:34"
        },
        {
            "Bibnr": "27361",
            "Name": "張庭淵",
            "OfficialTime": "01:54:52",
            "RankAll": "3417",
            "NetTime": "01:48:41"
        },
        {
            "Bibnr": "21597",
            "Name": "James Ng",
            "OfficialTime": "01:54:52",
            "RankAll": "3418",
            "NetTime": "01:50:24"
        },
        {
            "Bibnr": "19130",
            "Name": "何鳳敏",
            "OfficialTime": "01:54:52",
            "RankAll": "3419",
            "NetTime": "01:47:33"
        },
        {
            "Bibnr": "29596",
            "Name": "李威漢",
            "OfficialTime": "01:54:53",
            "RankAll": "3420",
            "NetTime": "01:51:09"
        },
        {
            "Bibnr": "20188",
            "Name": "Ng Wing Yan",
            "OfficialTime": "01:54:53",
            "RankAll": "3421",
            "NetTime": "01:52:18"
        },
        {
            "Bibnr": "26203",
            "Name": "廖俊翔",
            "OfficialTime": "01:54:53",
            "RankAll": "3422",
            "NetTime": "01:52:18"
        },
        {
            "Bibnr": "22331",
            "Name": "羅仁傑",
            "OfficialTime": "01:54:53",
            "RankAll": "3423",
            "NetTime": "01:49:14"
        },
        {
            "Bibnr": "29245",
            "Name": "黃啟豪",
            "OfficialTime": "01:54:53",
            "RankAll": "3424",
            "NetTime": "01:50:59"
        },
        {
            "Bibnr": "16333",
            "Name": "高筱雯",
            "OfficialTime": "01:54:53",
            "RankAll": "3425",
            "NetTime": "01:52:02"
        },
        {
            "Bibnr": "27646",
            "Name": "彭駿賢",
            "OfficialTime": "01:54:53",
            "RankAll": "3426",
            "NetTime": "01:52:05"
        },
        {
            "Bibnr": "23024",
            "Name": "廖克軒",
            "OfficialTime": "01:54:53",
            "RankAll": "3427",
            "NetTime": "01:46:34"
        },
        {
            "Bibnr": "28111",
            "Name": "江漢鐘",
            "OfficialTime": "01:54:53",
            "RankAll": "3428",
            "NetTime": "01:47:37"
        },
        {
            "Bibnr": "26723",
            "Name": "陳炳宏",
            "OfficialTime": "01:54:54",
            "RankAll": "3429",
            "NetTime": "01:53:35"
        },
        {
            "Bibnr": "29542",
            "Name": "劉逸聲",
            "OfficialTime": "01:54:54",
            "RankAll": "3430",
            "NetTime": "01:51:13"
        },
        {
            "Bibnr": "34153",
            "Name": "胡君弘",
            "OfficialTime": "01:54:55",
            "RankAll": "3431",
            "NetTime": "01:52:35"
        },
        {
            "Bibnr": "30122",
            "Name": "鄭羣耀",
            "OfficialTime": "01:54:55",
            "RankAll": "3432",
            "NetTime": "01:54:31"
        },
        {
            "Bibnr": "25226",
            "Name": "沈韋廷",
            "OfficialTime": "01:54:56",
            "RankAll": "3433",
            "NetTime": "01:49:58"
        },
        {
            "Bibnr": "27159",
            "Name": "蕭文政",
            "OfficialTime": "01:54:56",
            "RankAll": "3434",
            "NetTime": "01:51:33"
        },
        {
            "Bibnr": "25340",
            "Name": "楊守德",
            "OfficialTime": "01:54:56",
            "RankAll": "3435",
            "NetTime": "01:54:38"
        },
        {
            "Bibnr": "19155",
            "Name": "Yung Ka Wai",
            "OfficialTime": "01:54:57",
            "RankAll": "3436",
            "NetTime": "01:54:06"
        },
        {
            "Bibnr": "30320",
            "Name": "林乃鴻",
            "OfficialTime": "01:54:57",
            "RankAll": "3437",
            "NetTime": "01:51:46"
        },
        {
            "Bibnr": "21733",
            "Name": "林鴻儒",
            "OfficialTime": "01:54:57",
            "RankAll": "3438",
            "NetTime": "01:52:43"
        },
        {
            "Bibnr": "29362",
            "Name": "楊德傑",
            "OfficialTime": "01:54:58",
            "RankAll": "3439",
            "NetTime": "01:53:36"
        },
        {
            "Bibnr": "28798",
            "Name": "Logan",
            "OfficialTime": "01:54:58",
            "RankAll": "3440",
            "NetTime": "01:54:19"
        },
        {
            "Bibnr": "34726",
            "Name": "賴弘彬",
            "OfficialTime": "01:54:58",
            "RankAll": "3441",
            "NetTime": "01:54:19"
        },
        {
            "Bibnr": "16321",
            "Name": "Yulin Chen",
            "OfficialTime": "01:54:59",
            "RankAll": "3442",
            "NetTime": "01:52:54"
        },
        {
            "Bibnr": "25388",
            "Name": "張瑋倫",
            "OfficialTime": "01:54:59",
            "RankAll": "3443",
            "NetTime": "01:51:06"
        },
        {
            "Bibnr": "25317",
            "Name": "鄭孟凡",
            "OfficialTime": "01:55:00",
            "RankAll": "3444",
            "NetTime": "01:47:22"
        },
        {
            "Bibnr": "21460",
            "Name": "陳凱喬",
            "OfficialTime": "01:55:00",
            "RankAll": "3445",
            "NetTime": "01:53:26"
        },
        {
            "Bibnr": "21675",
            "Name": "應建凱",
            "OfficialTime": "01:55:01",
            "RankAll": "3446",
            "NetTime": "01:53:22"
        },
        {
            "Bibnr": "24484",
            "Name": "江誌仁",
            "OfficialTime": "01:55:01",
            "RankAll": "3447",
            "NetTime": "01:54:46"
        },
        {
            "Bibnr": "33272",
            "Name": "楊文進",
            "OfficialTime": "01:55:02",
            "RankAll": "3448",
            "NetTime": "01:50:49"
        },
        {
            "Bibnr": "25442",
            "Name": "黃智",
            "OfficialTime": "01:55:02",
            "RankAll": "3449",
            "NetTime": "01:47:52"
        },
        {
            "Bibnr": "35185",
            "Name": "王浩棠",
            "OfficialTime": "02:00:03",
            "RankAll": "3450",
            "NetTime": "02:00:03"
        },
        {
            "Bibnr": "20277",
            "Name": "邱堉惠",
            "OfficialTime": "01:55:03",
            "RankAll": "3451",
            "NetTime": "01:54:53"
        },
        {
            "Bibnr": "34753",
            "Name": "鄭立璿",
            "OfficialTime": "01:55:03",
            "RankAll": "3452",
            "NetTime": "01:49:01"
        },
        {
            "Bibnr": "36002",
            "Name": "KEN NAKAJIMA",
            "OfficialTime": "01:55:03",
            "RankAll": "3453",
            "NetTime": "01:48:43"
        },
        {
            "Bibnr": "23481",
            "Name": "姚和成",
            "OfficialTime": "01:55:04",
            "RankAll": "3454",
            "NetTime": "01:45:48"
        },
        {
            "Bibnr": "19747",
            "Name": "郭家麟",
            "OfficialTime": "01:55:04",
            "RankAll": "3455",
            "NetTime": "01:52:51"
        },
        {
            "Bibnr": "28094",
            "Name": "黃嵩仁",
            "OfficialTime": "01:55:05",
            "RankAll": "3456",
            "NetTime": "01:48:23"
        },
        {
            "Bibnr": "15595",
            "Name": "高于婷",
            "OfficialTime": "01:55:05",
            "RankAll": "3457",
            "NetTime": "01:52:35"
        },
        {
            "Bibnr": "29523",
            "Name": "詹紫華",
            "OfficialTime": "01:55:05",
            "RankAll": "3458",
            "NetTime": "01:52:36"
        },
        {
            "Bibnr": "14736",
            "Name": "林家竹",
            "OfficialTime": "01:55:06",
            "RankAll": "3459",
            "NetTime": "01:54:55"
        },
        {
            "Bibnr": "37099",
            "Name": "莊子緯",
            "OfficialTime": "01:55:06",
            "RankAll": "3460",
            "NetTime": "01:49:36"
        },
        {
            "Bibnr": "31753",
            "Name": "Vincent Pham",
            "OfficialTime": "01:55:07",
            "RankAll": "3461",
            "NetTime": "01:49:56"
        },
        {
            "Bibnr": "24174",
            "Name": "李汪獻",
            "OfficialTime": "01:55:08",
            "RankAll": "3462",
            "NetTime": "01:51:56"
        },
        {
            "Bibnr": "30571",
            "Name": "李哲瑋",
            "OfficialTime": "01:55:08",
            "RankAll": "3463",
            "NetTime": "01:52:51"
        },
        {
            "Bibnr": "25318",
            "Name": "岳喜聖",
            "OfficialTime": "01:55:09",
            "RankAll": "3464",
            "NetTime": "01:54:19"
        },
        {
            "Bibnr": "16313",
            "Name": "李蕙妍",
            "OfficialTime": "01:55:09",
            "RankAll": "3465",
            "NetTime": "01:53:31"
        },
        {
            "Bibnr": "17759",
            "Name": "Yve Chloi Mae M. Aclo",
            "OfficialTime": "01:55:09",
            "RankAll": "3466",
            "NetTime": "01:47:21"
        },
        {
            "Bibnr": "36408",
            "Name": "賴錫志",
            "OfficialTime": "01:55:10",
            "RankAll": "3467",
            "NetTime": "01:50:09"
        },
        {
            "Bibnr": "25312",
            "Name": "吳瑞騰",
            "OfficialTime": "01:55:10",
            "RankAll": "3468",
            "NetTime": "01:54:45"
        },
        {
            "Bibnr": "23309",
            "Name": "梁雍",
            "OfficialTime": "01:55:10",
            "RankAll": "3469",
            "NetTime": "01:48:26"
        },
        {
            "Bibnr": "20097",
            "Name": "pun cin lam lisa",
            "OfficialTime": "01:55:10",
            "RankAll": "3470",
            "NetTime": "01:53:28"
        },
        {
            "Bibnr": "23249",
            "Name": "Lam Tsz Man",
            "OfficialTime": "01:55:11",
            "RankAll": "3471",
            "NetTime": "01:47:26"
        },
        {
            "Bibnr": "19333",
            "Name": "王睿瑄",
            "OfficialTime": "01:55:11",
            "RankAll": "3472",
            "NetTime": "01:54:46"
        },
        {
            "Bibnr": "31715",
            "Name": "謝孟宏",
            "OfficialTime": "01:55:11",
            "RankAll": "3473",
            "NetTime": "01:47:44"
        },
        {
            "Bibnr": "27261",
            "Name": "陳文凱",
            "OfficialTime": "01:55:12",
            "RankAll": "3474",
            "NetTime": "01:51:45"
        },
        {
            "Bibnr": "29675",
            "Name": "Cheung Chi Haang",
            "OfficialTime": "01:55:12",
            "RankAll": "3475",
            "NetTime": "01:51:15"
        },
        {
            "Bibnr": "24202",
            "Name": "蔡忠憲",
            "OfficialTime": "01:55:12",
            "RankAll": "3476",
            "NetTime": "01:51:42"
        },
        {
            "Bibnr": "36091",
            "Name": "邵昉進",
            "OfficialTime": "01:55:13",
            "RankAll": "3477",
            "NetTime": "01:43:41"
        },
        {
            "Bibnr": "35858",
            "Name": "YOSHIDA HIDEKI",
            "OfficialTime": "01:55:13",
            "RankAll": "3478",
            "NetTime": "01:51:51"
        },
        {
            "Bibnr": "33258",
            "Name": "陳文榮",
            "OfficialTime": "01:55:14",
            "RankAll": "3479",
            "NetTime": "01:48:07"
        },
        {
            "Bibnr": "29502",
            "Name": "毛海戎",
            "OfficialTime": "01:55:14",
            "RankAll": "3480",
            "NetTime": "01:49:43"
        },
        {
            "Bibnr": "26604",
            "Name": "陳昌甫",
            "OfficialTime": "01:55:14",
            "RankAll": "3481",
            "NetTime": "01:54:12"
        },
        {
            "Bibnr": "26389",
            "Name": "廖俊男",
            "OfficialTime": "01:55:15",
            "RankAll": "3482",
            "NetTime": "01:54:52"
        },
        {
            "Bibnr": "25760",
            "Name": "許侑全",
            "OfficialTime": "01:55:15",
            "RankAll": "3483",
            "NetTime": "01:53:43"
        },
        {
            "Bibnr": "20474",
            "Name": "陳穎琪",
            "OfficialTime": "01:55:15",
            "RankAll": "3484",
            "NetTime": "01:49:41"
        },
        {
            "Bibnr": "37453",
            "Name": "陳鴻",
            "OfficialTime": "01:55:15",
            "RankAll": "3485",
            "NetTime": "01:50:55"
        },
        {
            "Bibnr": "33724",
            "Name": "童正雄",
            "OfficialTime": "01:55:15",
            "RankAll": "3486",
            "NetTime": "01:52:24"
        },
        {
            "Bibnr": "31445",
            "Name": "楊筑棨",
            "OfficialTime": "01:55:15",
            "RankAll": "3487",
            "NetTime": "01:53:48"
        },
        {
            "Bibnr": "32740",
            "Name": "江盛匡",
            "OfficialTime": "01:55:16",
            "RankAll": "3488",
            "NetTime": "01:53:42"
        },
        {
            "Bibnr": "25499",
            "Name": "顏仲祥",
            "OfficialTime": "01:55:16",
            "RankAll": "3489",
            "NetTime": "01:51:34"
        },
        {
            "Bibnr": "22620",
            "Name": "程偉晉",
            "OfficialTime": "01:55:17",
            "RankAll": "3490",
            "NetTime": "01:50:35"
        },
        {
            "Bibnr": "25218",
            "Name": "吳承融",
            "OfficialTime": "01:55:17",
            "RankAll": "3491",
            "NetTime": "01:52:21"
        },
        {
            "Bibnr": "34080",
            "Name": "黃祥瑋",
            "OfficialTime": "01:55:17",
            "RankAll": "3492",
            "NetTime": "01:53:20"
        },
        {
            "Bibnr": "16785",
            "Name": "徐郁婷",
            "OfficialTime": "01:55:18",
            "RankAll": "3493",
            "NetTime": "01:52:50"
        },
        {
            "Bibnr": "17647",
            "Name": "楊淑保",
            "OfficialTime": "01:55:18",
            "RankAll": "3494",
            "NetTime": "01:52:09"
        },
        {
            "Bibnr": "30048",
            "Name": "林立",
            "OfficialTime": "01:55:19",
            "RankAll": "3495",
            "NetTime": "01:54:22"
        },
        {
            "Bibnr": "34469",
            "Name": "Ricky Maulana Antrasena",
            "OfficialTime": "01:55:19",
            "RankAll": "3496",
            "NetTime": "01:45:15"
        },
        {
            "Bibnr": "30005",
            "Name": "吳佳鴻",
            "OfficialTime": "01:55:19",
            "RankAll": "3497",
            "NetTime": "01:48:46"
        },
        {
            "Bibnr": "21771",
            "Name": "王一傑",
            "OfficialTime": "01:55:20",
            "RankAll": "3498",
            "NetTime": "01:53:11"
        },
        {
            "Bibnr": "29577",
            "Name": "陳韋廷",
            "OfficialTime": "01:55:20",
            "RankAll": "3499",
            "NetTime": "01:52:15"
        },
        {
            "Bibnr": "30545",
            "Name": "龔伯諺",
            "OfficialTime": "01:55:20",
            "RankAll": "3500",
            "NetTime": "01:52:08"
        }
    ]
}